[
  {
    "chain-name": "arb-dev-test",
    "parent-chain-id": 11155111,
    "parent-chain-is-arbitrum": false,
    "sequencer-url": "",
    "secondary-forwarding-target": "",
    "feed-url": "",
    "secondary-feed-url": "",
    "das-index-url": "",
    "has-genesis-state": false,
    "chain-config": {
      "chainId": 412346,
      "homesteadBlock": 0,
      "daoForkSupport": true,
      "eip150Block": 0,
      "eip155Block": 0,
      "eip158Block": 0,
      "byzantiumBlock": 0,
      "constantinopleBlock": 0,
      "petersburgBlock": 0,
      "istanbulBlock": 0,
      "muirGlacierBlock": 0,
      "berlinBlock": 0,
      "londonBlock": 0,
      "clique": {
        "period": 0,
        "epoch": 0
      },
      "arbitrum": {
        "EnableArbOS": true,
        "AllowDebugPrecompiles": true,
        "DataAvailabilityCommittee": false,
        "InitialArbOSVersion": 11,
        "InitialChainOwner": "0x7bcd4b1d62de88cee1c08b785aadc807c1914531",
        "GenesisBlockNum": 0
      }
    },
    "rollup": {
      "bridge": "0x697a6dab0305cf13c5cbf810984857d63600893e",
      "inbox": "0xa08e310a4598e40d181b5c425fbee278ced5400a",
      "sequencer-inbox": "0x2951b887e53ed0af6a9713cda08f06b8af914498",
      "rollup": "0x11daa8241c971ebcf4fa99b791eacc5fe44b12b6",
      "native-token": "0x0000000000000000000000000000000000000000",
      "upgrade-executor": "0x0000000000000000000000000000000000000000",
      "validator-utils": "0x0000000000000000000000000000000000000000",
      "validator-wallet-creator": "0x18fe5e7eab7f81c5752a9df273b3d42e050a6443",
      "stake-token": "0x82bfb5be05b2b929fff73b715ca102fc832cd699",
      "deployed-at": 5146664
    }
  }
]
